niddk_covid_sicr/__init__.py
niddk_covid_sicr/analysis.py
niddk_covid_sicr/data.py
niddk_covid_sicr/io.py
niddk_covid_sicr/prep.py
niddk_covid_sicr/stats.py
covid_sicr-1.0.4.dist-info/METADATA
covid_sicr-1.0.4.dist-info/WHEEL
covid_sicr-1.0.4.dist-info/top_level.txt
covid_sicr-1.0.4.dist-info/RECORD
