Metadata-Version: 2.1
Name: covid-sicr
Version: 1.0.4
Summary: Global estimation of unobserved COVID-19 infection
Home-page: UNKNOWN
Author: NIDDK
License: MIT
Platform: UNKNOWN
Requires-Dist: arviz (>=0.5)
Requires-Dist: bs4
Requires-Dist: lxml
Requires-Dist: matplotlib (>=3.0)
Requires-Dist: numexpr
Requires-Dist: numpy (>=1.15)
Requires-Dist: pandas (>=1.0)
Requires-Dist: papermill
Requires-Dist: p-tqdm
Requires-Dist: pystan (>=2.19)
Requires-Dist: scipy
Requires-Dist: tqdm
